deksmb-0.1.2.dist-info/METADATA
deksmb-0.1.2.dist-info/WHEEL
deksmb-0.1.2.dist-info/entry_points.txt
deksmb/__init__.py
deksmb/click/__entry__.py
deksmb/click/__init__.py
deksmb/client/__init__.py
deksmb/client/base.py
deksmb/client/progress.py
deksmb-0.1.2.dist-info/RECORD
